sphinx_plantuml-1.0.0-py3.9-nspkg.pth
sphinxcontrib/plantuml/__init__.py
sphinxcontrib/plantuml/encode.py
sphinxcontrib/plantuml/plantuml.py
sphinx_plantuml-1.0.0.dist-info/LICENSE
sphinx_plantuml-1.0.0.dist-info/METADATA
sphinx_plantuml-1.0.0.dist-info/WHEEL
sphinx_plantuml-1.0.0.dist-info/namespace_packages.txt
sphinx_plantuml-1.0.0.dist-info/top_level.txt
sphinx_plantuml-1.0.0.dist-info/RECORD
