Metadata-Version: 2.1
Name: sphinx-plantuml
Version: 1.0.0
Summary: an extension for sphinx to render plantuml in sphinx documents
Home-page: https://github.com/zqmillet/sphinx-plantuml
Author: kinopico
Author-email: zqmillet@qq.com
License: UNKNOWN
Platform: UNKNOWN
License-File: LICENSE
Requires-Dist: docutils (==0.17.1)
Requires-Dist: Sphinx (==4.4.0)
